project_builder/__init__.py
project_builder/boiler_plates.py
project_builder/builder.py
project_builder/llm_interface.py
project_builder/main.py
project_builder/templates.py
project_builder/utils.py
tests/__init__.py
tests/test_project_builder.py
project_builder-0.1.0.dist-info/LICENSE
project_builder-0.1.0.dist-info/METADATA
project_builder-0.1.0.dist-info/WHEEL
project_builder-0.1.0.dist-info/top_level.txt
project_builder-0.1.0.dist-info/RECORD
